angle/CoreFunctions.py
angle/__init__.py
angle/angle-server.py
angle/ast_magic.py
angle/context.py
angle/english_parser.py
angle/english_tokens.py
angle/events.py
angle/exceptionz.py
angle/extension_functions.py
angle/extensions.py
angle/interpretation.py
angle/js_emitter.py
angle/module_method_map.py
angle/nodes.py
angle/power_parser.py
angle/pyc_emitter.py
angle/tree.py
angle-0.1.9.data/scripts/angle
angle-0.1.9.dist-info/DESCRIPTION.rst
angle-0.1.9.dist-info/METADATA
angle-0.1.9.dist-info/RECORD
angle-0.1.9.dist-info/WHEEL
angle-0.1.9.dist-info/dependency_links.txt
angle-0.1.9.dist-info/metadata.json
angle-0.1.9.dist-info/top_level.txt
kast/__init__.py
kast/ast_export.py
kast/ast_import.py
kast/kast.py
kast/kast_util.py
kast/xast.py
kast/tests/__init__.py
kast/tests/_global.py
kast/tests/hi.py
kast/tests/kast_import.py
kast/tests/scratchpad.py
kast/tests/test.py
kast/tests/test.xast.py
kast/tests/test_ast_writer.py
kast/tests/test_js6_export.py
kast/tests/transforms/__init__.py
kast/tests/transforms/js6_export.py
kast/tests/transforms/kast_rewriter.py
kast/tests/transforms/norm-kast-xml.py
kast/transforms/__init__.py
kast/transforms/js6_export.py
kast/transforms/kast_rewriter.py
kast/transforms/norm-kast-xml.py
tests/__init__.py
tests/algebra_test.py
tests/ast_eval_inline.py
tests/ast_test_inline.py
tests/bash_test.py
tests/blank_test.py
tests/block_test.py
tests/comment_test.py
tests/compiler_test.py
tests/condition_test.py
tests/emitter_test.py
tests/error_test.py
tests/function_test.py
tests/function_test_ok.py
tests/future_test.py
tests/hash_test.py
tests/init.py
tests/javascript_test.py
tests/job_task_promise_test.py
tests/list_test.py
tests/loop_test.py
tests/mac_test.py
tests/method_test.py
tests/number_test.py
tests/observer_test.py
tests/package_test.py
tests/parser_test.py
tests/parser_test_helper.py
tests/property_test.py
tests/python_test.py
tests/regex_test.py
tests/samples_test.py
tests/selector_test.py
tests/self_compile_test.py
tests/setter_test.py
tests/string_test.py
tests/test_algebra.py
tests/tree_test.py
tests/type_test.py
tests/unicode_test.py
tests/variable_test.py
tests/transforms/__init__.py
