Metadata-Version: 2.0
Name: angle
Version: 0.1.9
Summary: Angle : speakable programming language compiling to python bytecode
Home-page: UNKNOWN
Author: Pannous
Author-email: info@pannous.com
License: Apache2 license
Platform: UNKNOWN
Requires-Dist: argparse
Requires-Dist: astor
Requires-Dist: pyyaml
Requires-Dist: stem
